[
  {
    "city": "千代田区",
    "city_en": "Chiyoda-ku",
    "Ec": 77.5143855,
    "Re": 71.60854394,
    "Cu": 72.89866419,
    "Li": 73.9668197,
    "En": 53.50526217,
    "Ac": 73.36221055
  },
  {
    "city": "中央区",
    "city_en": "Chuo-ku",
    "Ec": 68.14160432,
    "Re": 53.25290742,
    "Cu": 56.05969967,
    "Li": 69.93394665,
    "En": 72.51367489,
    "Ac": 70.70091296
  },
  {
    "city": "港区",
    "city_en": "Minato-ku",
    "Ec": 69.17276625,
    "Re": 76.76024119,
    "Cu": 72.47082752,
    "Li": 67.29577175,
    "En": 53.78618726,
    "Ac": 62.57354332
  },
  {
    "city": "新宿区",
    "city_en": "Shinjuku-ku",
    "Ec": 55.37451972,
    "Re": 63.55321611,
    "Cu": 59.1700177,
    "Li": 55.97663644,
    "En": 38.15242986,
    "Ac": 56.72603794
  },
  {
    "city": "文京区",
    "city_en": "Bunkyo-ku",
    "Ec": 51.4895018,
    "Re": 70.48923144,
    "Cu": 53.44143556,
    "Li": 61.03300034,
    "En": 51.56186015,
    "Ac": 53.07914264
  },
  {
    "city": "台東区",
    "city_en": "Taito-ku",
    "Ec": 47.69360038,
    "Re": 43.91595822,
    "Cu": 58.05844274,
    "Li": 52.17096206,
    "En": 40.05186041,
    "Ac": 57.48809591
  },
  {
    "city": "墨田区",
    "city_en": "Sumida-ku",
    "Ec": 45.78599614,
    "Re": 43.17949864,
    "Cu": 50.97335277,
    "Li": 45.14762335,
    "En": 51.31567533,
    "Ac": 46.56676299
  },
  {
    "city": "江東区",
    "city_en": "Koto-ku",
    "Ec": 49.27749488,
    "Re": 48.16164717,
    "Cu": 60.56178402,
    "Li": 40.73332555,
    "En": 73.89681985,
    "Ac": 55.34386819
  },
  {
    "city": "品川区",
    "city_en": "Shinagawa-ku",
    "Ec": 52.84271566,
    "Re": 47.02633285,
    "Cu": 49.13784168,
    "Li": 48.35618331,
    "En": 52.66920788,
    "Ac": 56.25018206
  },
  {
    "city": "目黒区",
    "city_en": "Meguro-ku",
    "Ec": 51.00419561,
    "Re": 49.77101632,
    "Cu": 44.92818245,
    "Li": 51.21627721,
    "En": 49.20446904,
    "Ac": 46.66613346
  },
  {
    "city": "大田区",
    "city_en": "Ota-ku",
    "Ec": 44.81592854,
    "Re": 47.35175228,
    "Cu": 45.00577838,
    "Li": 41.26019597,
    "En": 46.99001776,
    "Ac": 51.33661012
  },
  {
    "city": "世田谷区",
    "city_en": "Setagaya-ku",
    "Ec": 46.72528433,
    "Re": 47.41848148,
    "Cu": 47.01570955,
    "Li": 49.51132642,
    "En": 54.59344762,
    "Ac": 42.16837977
  },
  {
    "city": "渋谷区",
    "city_en": "Shibuya-ku",
    "Ec": 61.48190285,
    "Re": 48.64753631,
    "Cu": 61.45393377,
    "Li": 58.07030818,
    "En": 39.06783762,
    "Ac": 58.27157622
  },
  {
    "city": "中野区",
    "city_en": "Nakano-ku",
    "Ec": 46.90193242,
    "Re": 43.57745916,
    "Cu": 43.2145493,
    "Li": 42.92293947,
    "En": 43.21154164,
    "Ac": 45.89776854
  },
  {
    "city": "杉並区",
    "city_en": "Suginami-ku",
    "Ec": 45.90003354,
    "Re": 42.77641472,
    "Cu": 42.90646825,
    "Li": 48.04399739,
    "En": 54.88819384,
    "Ac": 40.66491611
  },
  {
    "city": "豊島区",
    "city_en": "Toshima-ku",
    "Ec": 48.84165468,
    "Re": 47.28115768,
    "Cu": 50.35885852,
    "Li": 50.57007524,
    "En": 30.27143357,
    "Ac": 50.80603923
  },
  {
    "city": "北区",
    "city_en": "Kita-ku",
    "Ec": 42.28878447,
    "Re": 43.55854819,
    "Cu": 40.41286712,
    "Li": 39.69531494,
    "En": 48.42305056,
    "Ac": 36.41151251
  },
  {
    "city": "荒川区",
    "city_en": "Arakawa-ku",
    "Ec": 43.24132827,
    "Re": 43.99322277,
    "Cu": 37.95896601,
    "Li": 44.06459374,
    "En": 45.01377157,
    "Ac": 45.35596904
  },
  {
    "city": "板橋区",
    "city_en": "Itabashi-ku",
    "Ec": 42.34815898,
    "Re": 44.65441272,
    "Cu": 39.17515883,
    "Li": 48.45325073,
    "En": 40.51314621,
    "Ac": 40.4543693
  },
  {
    "city": "練馬区",
    "city_en": "Nerima-ku",
    "Ec": 40.85147765,
    "Re": 43.54942589,
    "Cu": 41.08838797,
    "Li": 45.97425379,
    "En": 55.92937885,
    "Ac": 35.86868185
  },
  {
    "city": "足立区",
    "city_en": "Adachi-ku",
    "Ec": 38.87704051,
    "Re": 43.31060717,
    "Cu": 39.08592961,
    "Li": 37.57476073,
    "En": 40.84533019,
    "Ac": 41.55272857
  },
  {
    "city": "葛飾区",
    "city_en": "Katsushika-ku",
    "Ec": 38.57611733,
    "Re": 44.19847394,
    "Cu": 43.25815021,
    "Li": 39.89807192,
    "En": 54.98145591,
    "Ac": 39.25204449
  },
  {
    "city": "江戸川区",
    "city_en": "Edogawa-ku",
    "Ec": 40.85357616,
    "Re": 41.96391438,
    "Cu": 41.36499419,
    "Li": 38.13036511,
    "En": 58.61394782,
    "Ac": 43.20251423
  }
]